contingency_space/__init__.py
contingency_space/cm_generator.py
contingency_space/confusion_matrix.py
contingency_space/contingency_space.py
contingency_space/imbalance_sensitivity.py
contingency_space-0.1.9.dist-info/METADATA
contingency_space-0.1.9.dist-info/WHEEL
contingency_space-0.1.9.dist-info/RECORD
