Metadata-Version: 2.4
Name: contingency_space
Version: 0.1.9
Summary: A package for creating and analyzing contingency spaces.
Project-URL: Homepage, https://github.com
Project-URL: Issues, https://github.com
Author-email: Colin Kehoe <cdknnz@umsl.edu>
License-Expression: MIT
Classifier: License :: OSI Approved :: MIT License
Classifier: Programming Language :: Python :: 3.5
Requires-Python: >=3.5
